<?xml version="1.0" encoding="UTF-8"?>
<quiz>
<!-- question: 2579921  -->
  <question type="multichoice">
    <name>
      <text>CH5.3-101</text>
    </name>
    <questiontext format="html">
      <text><![CDATA[<p dir="ltr" style="text-align: left;">下列不属于信息社会的基本特征的是(　　)。<br></p>]]></text>
    </questiontext>
    <generalfeedback format="html">
      <text></text>
    </generalfeedback>
    <defaultgrade>1.0000000</defaultgrade>
    <penalty>0.3333333</penalty>
    <hidden>0</hidden>
    <idnumber></idnumber>
    <single>true</single>
    <shuffleanswers>true</shuffleanswers>
    <answernumbering>none</answernumbering>
    <showstandardinstruction>0</showstandardinstruction>
    <correctfeedback format="html">
      <text>您的答案是正确的。</text>
    </correctfeedback>
    <partiallycorrectfeedback format="html">
      <text>您的答案部分正确。</text>
    </partiallycorrectfeedback>
    <incorrectfeedback format="html">
      <text>您的答案不正确</text>
    </incorrectfeedback>
    <shownumcorrect/>
    <answer fraction="0" format="html">
      <text><![CDATA[<p dir="ltr" style="text-align: left;">知识性经济<br></p>]]></text>
      <feedback format="html">
        <text></text>
      </feedback>
    </answer>
    <answer fraction="0" format="html">
      <text><![CDATA[<p dir="ltr" style="text-align: left;">网络化服务<br></p>]]></text>
      <feedback format="html">
        <text></text>
      </feedback>
    </answer>
    <answer fraction="0" format="html">
      <text><![CDATA[<p dir="ltr" style="text-align: left;">数字化生活<br></p>]]></text>
      <feedback format="html">
        <text></text>
      </feedback>
    </answer>
    <answer fraction="100" format="html">
      <text><![CDATA[<p dir="ltr" style="text-align: left;">人性化管理<br></p>]]></text>
      <feedback format="html">
        <text></text>
      </feedback>
    </answer>
  </question>

<!-- question: 2579923  -->
  <question type="multichoice">
    <name>
      <text>CH5.3-102</text>
    </name>
    <questiontext format="html">
      <text><![CDATA[<p dir="ltr" style="text-align: left;">信息社会赖以生存的三大资源不包括(　　)。<br></p>]]></text>
    </questiontext>
    <generalfeedback format="html">
      <text></text>
    </generalfeedback>
    <defaultgrade>1.0000000</defaultgrade>
    <penalty>0.3333333</penalty>
    <hidden>0</hidden>
    <idnumber></idnumber>
    <single>true</single>
    <shuffleanswers>true</shuffleanswers>
    <answernumbering>none</answernumbering>
    <showstandardinstruction>0</showstandardinstruction>
    <correctfeedback format="html">
      <text>您的答案是正确的。</text>
    </correctfeedback>
    <partiallycorrectfeedback format="html">
      <text>您的答案部分正确。</text>
    </partiallycorrectfeedback>
    <incorrectfeedback format="html">
      <text>您的答案不正确</text>
    </incorrectfeedback>
    <shownumcorrect/>
    <answer fraction="100" format="html">
      <text><![CDATA[<p dir="ltr" style="text-align: left;">数据<br></p>]]></text>
      <feedback format="html">
        <text></text>
      </feedback>
    </answer>
    <answer fraction="0" format="html">
      <text><![CDATA[<p dir="ltr" style="text-align: left;">信息<br></p>]]></text>
      <feedback format="html">
        <text></text>
      </feedback>
    </answer>
    <answer fraction="0" format="html">
      <text><![CDATA[<p dir="ltr" style="text-align: left;">物质<br></p>]]></text>
      <feedback format="html">
        <text></text>
      </feedback>
    </answer>
    <answer fraction="0" format="html">
      <text><![CDATA[<p dir="ltr" style="text-align: left;">能量<br></p>]]></text>
      <feedback format="html">
        <text></text>
      </feedback>
    </answer>
  </question>

<!-- question: 2579925  -->
  <question type="multichoice">
    <name>
      <text>CH5.3-103</text>
    </name>
    <questiontext format="html">
      <text><![CDATA[<p dir="ltr" style="text-align: left;">在信息社会，对劳动者的基本要求是(　　)。<br></p>]]></text>
    </questiontext>
    <generalfeedback format="html">
      <text></text>
    </generalfeedback>
    <defaultgrade>1.0000000</defaultgrade>
    <penalty>0.3333333</penalty>
    <hidden>0</hidden>
    <idnumber></idnumber>
    <single>true</single>
    <shuffleanswers>true</shuffleanswers>
    <answernumbering>none</answernumbering>
    <showstandardinstruction>0</showstandardinstruction>
    <correctfeedback format="html">
      <text>您的答案是正确的。</text>
    </correctfeedback>
    <partiallycorrectfeedback format="html">
      <text>您的答案部分正确。</text>
    </partiallycorrectfeedback>
    <incorrectfeedback format="html">
      <text>您的答案不正确</text>
    </incorrectfeedback>
    <shownumcorrect/>
    <answer fraction="0" format="html">
      <text><![CDATA[<p dir="ltr" style="text-align: left;">技术<br></p>]]></text>
      <feedback format="html">
        <text></text>
      </feedback>
    </answer>
    <answer fraction="0" format="html">
      <text><![CDATA[<p dir="ltr" style="text-align: left;">艺术<br></p>]]></text>
      <feedback format="html">
        <text></text>
      </feedback>
    </answer>
    <answer fraction="100" format="html">
      <text><![CDATA[<p dir="ltr" style="text-align: left;">知识<br></p>]]></text>
      <feedback format="html">
        <text></text>
      </feedback>
    </answer>
    <answer fraction="0" format="html">
      <text><![CDATA[<p dir="ltr" style="text-align: left;">能量<br></p>]]></text>
      <feedback format="html">
        <text></text>
      </feedback>
    </answer>
  </question>

<!-- question: 2579927  -->
  <question type="multichoice">
    <name>
      <text>CH5.3-104</text>
    </name>
    <questiontext format="html">
      <text><![CDATA[<p dir="ltr" style="text-align: left;">信息依赖可能带来的健康问题不包括(　　)。<br></p>]]></text>
    </questiontext>
    <generalfeedback format="html">
      <text></text>
    </generalfeedback>
    <defaultgrade>1.0000000</defaultgrade>
    <penalty>0.3333333</penalty>
    <hidden>0</hidden>
    <idnumber></idnumber>
    <single>true</single>
    <shuffleanswers>true</shuffleanswers>
    <answernumbering>none</answernumbering>
    <showstandardinstruction>0</showstandardinstruction>
    <correctfeedback format="html">
      <text>您的答案是正确的。</text>
    </correctfeedback>
    <partiallycorrectfeedback format="html">
      <text>您的答案部分正确。</text>
    </partiallycorrectfeedback>
    <incorrectfeedback format="html">
      <text>您的答案不正确</text>
    </incorrectfeedback>
    <shownumcorrect/>
    <answer fraction="0" format="html">
      <text><![CDATA[<p dir="ltr" style="text-align: left;">人际交往障碍<br></p>]]></text>
      <feedback format="html">
        <text></text>
      </feedback>
    </answer>
    <answer fraction="100" format="html">
      <text><![CDATA[<p dir="ltr" style="text-align: left;">幽闭恐惧症<br></p>]]></text>
      <feedback format="html">
        <text></text>
      </feedback>
    </answer>
    <answer fraction="0" format="html">
      <text><![CDATA[<p dir="ltr" style="text-align: left;">视力下降<br></p>]]></text>
      <feedback format="html">
        <text></text>
      </feedback>
    </answer>
    <answer fraction="0" format="html">
      <text><![CDATA[<p dir="ltr" style="text-align: left;">颈椎疼痛<br></p>]]></text>
      <feedback format="html">
        <text></text>
      </feedback>
    </answer>
  </question>

<!-- question: 2579929  -->
  <question type="multichoice">
    <name>
      <text>CH5.3-105</text>
    </name>
    <questiontext format="html">
      <text><![CDATA[<p dir="ltr" style="text-align: left;">下列不属于信息犯罪的是(　　)。<br></p>]]></text>
    </questiontext>
    <generalfeedback format="html">
      <text></text>
    </generalfeedback>
    <defaultgrade>1.0000000</defaultgrade>
    <penalty>0.3333333</penalty>
    <hidden>0</hidden>
    <idnumber></idnumber>
    <single>true</single>
    <shuffleanswers>true</shuffleanswers>
    <answernumbering>none</answernumbering>
    <showstandardinstruction>0</showstandardinstruction>
    <correctfeedback format="html">
      <text>您的答案是正确的。</text>
    </correctfeedback>
    <partiallycorrectfeedback format="html">
      <text>您的答案部分正确。</text>
    </partiallycorrectfeedback>
    <incorrectfeedback format="html">
      <text>您的答案不正确</text>
    </incorrectfeedback>
    <shownumcorrect/>
    <answer fraction="100" format="html">
      <text><![CDATA[<p dir="ltr" style="text-align: left;">信息污染<br></p>]]></text>
      <feedback format="html">
        <text></text>
      </feedback>
    </answer>
    <answer fraction="0" format="html">
      <text><![CDATA[<p dir="ltr" style="text-align: left;">信息窃取<br></p>]]></text>
      <feedback format="html">
        <text></text>
      </feedback>
    </answer>
    <answer fraction="0" format="html">
      <text><![CDATA[<p dir="ltr" style="text-align: left;">信息欺诈<br></p>]]></text>
      <feedback format="html">
        <text></text>
      </feedback>
    </answer>
    <answer fraction="0" format="html">
      <text><![CDATA[<p dir="ltr" style="text-align: left;">信息攻击<br></p>]]></text>
      <feedback format="html">
        <text></text>
      </feedback>
    </answer>
  </question>

<!-- question: 2579931  -->
  <question type="multichoice">
    <name>
      <text>CH5.3-106</text>
    </name>
    <questiontext format="html">
      <text><![CDATA[<p dir="ltr" style="text-align: left;">面对信息泛滥、信息污染等问题，我们必须提高自己的信息(　　)。<br></p>]]></text>
    </questiontext>
    <generalfeedback format="html">
      <text></text>
    </generalfeedback>
    <defaultgrade>1.0000000</defaultgrade>
    <penalty>0.3333333</penalty>
    <hidden>0</hidden>
    <idnumber></idnumber>
    <single>true</single>
    <shuffleanswers>true</shuffleanswers>
    <answernumbering>none</answernumbering>
    <showstandardinstruction>0</showstandardinstruction>
    <correctfeedback format="html">
      <text>您的答案是正确的。</text>
    </correctfeedback>
    <partiallycorrectfeedback format="html">
      <text>您的答案部分正确。</text>
    </partiallycorrectfeedback>
    <incorrectfeedback format="html">
      <text>您的答案不正确</text>
    </incorrectfeedback>
    <shownumcorrect/>
    <answer fraction="0" format="html">
      <text><![CDATA[<p dir="ltr" style="text-align: left;">获取能力<br></p>]]></text>
      <feedback format="html">
        <text></text>
      </feedback>
    </answer>
    <answer fraction="0" format="html">
      <text><![CDATA[<p dir="ltr" style="text-align: left;">加工能力<br></p>]]></text>
      <feedback format="html">
        <text></text>
      </feedback>
    </answer>
    <answer fraction="0" format="html">
      <text><![CDATA[<p dir="ltr" style="text-align: left;">编程能力<br></p>]]></text>
      <feedback format="html">
        <text></text>
      </feedback>
    </answer>
    <answer fraction="100" format="html">
      <text><![CDATA[<p dir="ltr" style="text-align: left;">甄别能力<br></p>]]></text>
      <feedback format="html">
        <text></text>
      </feedback>
    </answer>
  </question>

<!-- question: 2579933  -->
  <question type="multichoice">
    <name>
      <text>CH5.3-201</text>
    </name>
    <questiontext format="html">
      <text><![CDATA[<p dir="ltr" style="text-align: left;">信息技术大力促进科学技术的快速发展，其表现在(　　)。<br></p>]]></text>
    </questiontext>
    <generalfeedback format="html">
      <text></text>
    </generalfeedback>
    <defaultgrade>1.0000000</defaultgrade>
    <penalty>0.3333333</penalty>
    <hidden>0</hidden>
    <idnumber></idnumber>
    <single>false</single>
    <shuffleanswers>true</shuffleanswers>
    <answernumbering>none</answernumbering>
    <showstandardinstruction>0</showstandardinstruction>
    <correctfeedback format="html">
      <text>您的答案是正确的。</text>
    </correctfeedback>
    <partiallycorrectfeedback format="html">
      <text>您的答案部分正确。</text>
    </partiallycorrectfeedback>
    <incorrectfeedback format="html">
      <text>您的答案不正确</text>
    </incorrectfeedback>
    <shownumcorrect/>
    <answer fraction="33.33333" format="html">
      <text><![CDATA[<p dir="ltr" style="text-align: left;">计算机仿真技术可以模拟各种现实情况，便于验证科学假设<br></p>]]></text>
      <feedback format="html">
        <text></text>
      </feedback>
    </answer>
    <answer fraction="33.33333" format="html">
      <text>以微电子技术为中心的信息技术带动了空间开发、新能源开发和生物工程等尖端技术</text>
      <feedback format="html">
        <text></text>
      </feedback>
    </answer>
    <answer fraction="33.33333" format="html">
      <text><![CDATA[<p dir="ltr" style="text-align: left;">信息技术与其他学科的融合，促进了新兴学科和交叉学科的产生与发展<br></p>]]></text>
      <feedback format="html">
        <text></text>
      </feedback>
    </answer>
    <answer fraction="-100" format="html">
      <text><![CDATA[<p dir="ltr" style="text-align: left;">信息技术的突破性进展将会进一步改变世界的竞争格局<br></p>]]></text>
      <feedback format="html">
        <text></text>
      </feedback>
    </answer>
  </question>

<!-- question: 2579935  -->
  <question type="multichoice">
    <name>
      <text>CH5.3-202</text>
    </name>
    <questiontext format="html">
      <text><![CDATA[<p dir="ltr" style="text-align: left;">数字化信息成为信息社会的主要内容，主要表现为(　　)。<br></p>]]></text>
    </questiontext>
    <generalfeedback format="html">
      <text></text>
    </generalfeedback>
    <defaultgrade>1.0000000</defaultgrade>
    <penalty>0.3333333</penalty>
    <hidden>0</hidden>
    <idnumber></idnumber>
    <single>false</single>
    <shuffleanswers>true</shuffleanswers>
    <answernumbering>none</answernumbering>
    <showstandardinstruction>0</showstandardinstruction>
    <correctfeedback format="html">
      <text>您的答案是正确的。</text>
    </correctfeedback>
    <partiallycorrectfeedback format="html">
      <text>您的答案部分正确。</text>
    </partiallycorrectfeedback>
    <incorrectfeedback format="html">
      <text>您的答案不正确</text>
    </incorrectfeedback>
    <shownumcorrect/>
    <answer fraction="-100" format="html">
      <text><![CDATA[<p dir="ltr" style="text-align: left;">生活意义数字化<br></p>]]></text>
      <feedback format="html">
        <text></text>
      </feedback>
    </answer>
    <answer fraction="33.33333" format="html">
      <text><![CDATA[<p dir="ltr" style="text-align: left;">生活方式数字化<br></p>]]></text>
      <feedback format="html">
        <text></text>
      </feedback>
    </answer>
    <answer fraction="33.33333" format="html">
      <text><![CDATA[<p dir="ltr" style="text-align: left;">生活内容数字化<br></p>]]></text>
      <feedback format="html">
        <text></text>
      </feedback>
    </answer>
    <answer fraction="33.33333" format="html">
      <text><![CDATA[<p dir="ltr" style="text-align: left;">生活工具数字化<br></p>]]></text>
      <feedback format="html">
        <text></text>
      </feedback>
    </answer>
  </question>

<!-- question: 2579937  -->
  <question type="multichoice">
    <name>
      <text>CH5.3-203</text>
    </name>
    <questiontext format="html">
      <text><![CDATA[<p dir="ltr" style="text-align: left;">信息技术引发的社会问题包括(　　)。<br></p>]]></text>
    </questiontext>
    <generalfeedback format="html">
      <text></text>
    </generalfeedback>
    <defaultgrade>1.0000000</defaultgrade>
    <penalty>0.3333333</penalty>
    <hidden>0</hidden>
    <idnumber></idnumber>
    <single>false</single>
    <shuffleanswers>true</shuffleanswers>
    <answernumbering>none</answernumbering>
    <showstandardinstruction>0</showstandardinstruction>
    <correctfeedback format="html">
      <text>您的答案是正确的。</text>
    </correctfeedback>
    <partiallycorrectfeedback format="html">
      <text>您的答案部分正确。</text>
    </partiallycorrectfeedback>
    <incorrectfeedback format="html">
      <text>您的答案不正确</text>
    </incorrectfeedback>
    <shownumcorrect/>
    <answer fraction="25" format="html">
      <text><![CDATA[<p dir="ltr" style="text-align: left;">信息泛滥<br></p>]]></text>
      <feedback format="html">
        <text></text>
      </feedback>
    </answer>
    <answer fraction="25" format="html">
      <text><![CDATA[<p dir="ltr" style="text-align: left;">信息污染<br></p>]]></text>
      <feedback format="html">
        <text></text>
      </feedback>
    </answer>
    <answer fraction="25" format="html">
      <text><![CDATA[<p dir="ltr" style="text-align: left;">信息犯罪<br></p>]]></text>
      <feedback format="html">
        <text></text>
      </feedback>
    </answer>
    <answer fraction="25" format="html">
      <text><![CDATA[<p dir="ltr" style="text-align: left;">网络沉迷<br></p>]]></text>
      <feedback format="html">
        <text></text>
      </feedback>
    </answer>
  </question>

<!-- question: 2579939  -->
  <question type="multichoice">
    <name>
      <text>CH5.3-204</text>
    </name>
    <questiontext format="html">
      <text><![CDATA[<p dir="ltr" style="text-align: left;">信息技术的发展促进了学习方式的变革，学习更加(　　)。<br></p>]]></text>
    </questiontext>
    <generalfeedback format="html">
      <text></text>
    </generalfeedback>
    <defaultgrade>1.0000000</defaultgrade>
    <penalty>0.3333333</penalty>
    <hidden>0</hidden>
    <idnumber></idnumber>
    <single>false</single>
    <shuffleanswers>true</shuffleanswers>
    <answernumbering>none</answernumbering>
    <showstandardinstruction>0</showstandardinstruction>
    <correctfeedback format="html">
      <text>您的答案是正确的。</text>
    </correctfeedback>
    <partiallycorrectfeedback format="html">
      <text>您的答案部分正确。</text>
    </partiallycorrectfeedback>
    <incorrectfeedback format="html">
      <text>您的答案不正确</text>
    </incorrectfeedback>
    <shownumcorrect/>
    <answer fraction="25" format="html">
      <text><![CDATA[<p dir="ltr" style="text-align: left;">开放化</p>]]></text>
      <feedback format="html">
        <text></text>
      </feedback>
    </answer>
    <answer fraction="25" format="html">
      <text><![CDATA[<p dir="ltr" style="text-align: left;">大众化<br></p>]]></text>
      <feedback format="html">
        <text></text>
      </feedback>
    </answer>
    <answer fraction="25" format="html">
      <text><![CDATA[<p dir="ltr" style="text-align: left;">网络化<br></p>]]></text>
      <feedback format="html">
        <text></text>
      </feedback>
    </answer>
    <answer fraction="25" format="html">
      <text><![CDATA[<p dir="ltr" style="text-align: left;">个性化<br></p>]]></text>
      <feedback format="html">
        <text></text>
      </feedback>
    </answer>
  </question>

</quiz>